[
    {
        "TITULO": "Regata Basqueteira Vermelho ",
        "LINK": "https://www.integralmedica.com.br/regata-basqueteira-vermelho/p",
        "FIGURA": "https://integralmedica.vtexassets.com/arquivos/ids/164348-500-auto?v=638730602960730000&width=500&height=auto&aspect=true",
        "PRECO_ANTERIOR": null,
        "PRECO_PRINCIPAL": "R$110,90",
        "PARCELAMENTO": "em até2x deR$55,45",
        "OFF": "",
        "BENEFICIOS": [],
        "DESCRICAO": ""
    },
    {
        "TITULO": "Hoodie Integralmedica Red Camouflage ",
        "LINK": "https://www.integralmedica.com.br/hoddie-red-camouflage/p",
        "FIGURA": "https://integralmedica.vtexassets.com/arquivos/ids/159036-500-auto?v=638971865318400000&width=500&height=auto&aspect=true",
        "PRECO_ANTERIOR": null,
        "PRECO_PRINCIPAL": "R$346,90",
        "PARCELAMENTO": "em até6x deR$57,81",
        "OFF": "",
        "BENEFICIOS": [],
        "DESCRICAO": ""
    },
    {
        "TITULO": "Regata Wide Integralteam Vermelho ",
        "LINK": "https://www.integralmedica.com.br/regata-wide-integralteam-vermelho/p",
        "FIGURA": "https://integralmedica.vtexassets.com/arquivos/ids/164544-500-auto?v=638920114901000000&width=500&height=auto&aspect=true",
        "PRECO_ANTERIOR": null,
        "PRECO_PRINCIPAL": "R$104,90",
        "PARCELAMENTO": "em até2x deR$52,45",
        "OFF": "",
        "BENEFICIOS": [],
        "DESCRICAO": ""
    }
]